isic4kit/__init__.py
isic4kit/base.py
isic4kit/data/ar.json
isic4kit/data/en.json
isic4kit/isic4.py
isic4kit/loader.py
isic4kit/models.py
isic4kit/search.py
isic4kit/tree.py
isic4kit-0.0.5.dist-info/LICENCE
isic4kit-0.0.5.dist-info/METADATA
isic4kit-0.0.5.dist-info/WHEEL
isic4kit-0.0.5.dist-info/RECORD
