Metadata-Version: 2.1
Name: isic4kit
Version: 0.0.5
Summary: A Python SDK Library for working with the International Standard Industrial Classification of All Economic Activities (ISIC), Revision 4.
Author: Abdullah Alqahtani
Author-email: anqorithm@protonmail.com
Requires-Python: >=3.8,<4.0
Classifier: Programming Language :: Python :: 3
Classifier: Programming Language :: Python :: 3.8
Classifier: Programming Language :: Python :: 3.9
Classifier: Programming Language :: Python :: 3.10
Classifier: Programming Language :: Python :: 3.11
Classifier: Programming Language :: Python :: 3.12
Requires-Dist: pydantic (>=2.10.6,<3.0.0)
Requires-Dist: pytest (>=8.3.4,<9.0.0)
